odoo10_addon_procurement_operating_unit-10.0.1.0.0-py2.7-nspkg.pth
odoo10_addon_procurement_operating_unit-10.0.1.0.0.dist-info/top_level.txt
odoo10_addon_procurement_operating_unit-10.0.1.0.0.dist-info/WHEEL
odoo10_addon_procurement_operating_unit-10.0.1.0.0.dist-info/RECORD
odoo10_addon_procurement_operating_unit-10.0.1.0.0.dist-info/metadata.json
odoo10_addon_procurement_operating_unit-10.0.1.0.0.dist-info/DESCRIPTION.rst
odoo10_addon_procurement_operating_unit-10.0.1.0.0.dist-info/METADATA
odoo10_addon_procurement_operating_unit-10.0.1.0.0.dist-info/namespace_packages.txt
odoo/addons/procurement_operating_unit/__manifest__.py
odoo/addons/procurement_operating_unit/__init__.py
odoo/addons/procurement_operating_unit/README.rst
odoo/addons/procurement_operating_unit/security/procurement_security.xml
odoo/addons/procurement_operating_unit/static/description/icon.png
